macrokeyd/__init__.py
macrokeyd/assets/banner.png
macrokeyd/assets/icon32x32.png
macrokeyd/assets/icon64x64.png
macrokeyd/common/__init__.py
macrokeyd/common/config.py
macrokeyd/common/env_utils.py
macrokeyd/common/logger.py
macrokeyd/dbus/__init__.py
macrokeyd/dbus/main.py
macrokeyd/keyboard/__init__.py
macrokeyd/keyboard/actions.py
macrokeyd/keyboard/devices.py
macrokeyd/keyboard/main.py
macrokeyd/keyboard/macros/default.json
macrokeyd/keyboard/macros/gaming_pad.json
macrokeyd/scripts/install_service.py
macrokeyd/scripts/install_service.sh
macrokeyd/scripts/uninstall_service.py
macrokeyd/scripts/uninstall_service.sh
macrokeyd/ui/__init__.py
macrokeyd/ui/main.py
macrokeyd-0.1.11.dist-info/licenses/LICENCE
macrokeyd-0.1.11.dist-info/METADATA
macrokeyd-0.1.11.dist-info/WHEEL
macrokeyd-0.1.11.dist-info/entry_points.txt
macrokeyd-0.1.11.dist-info/top_level.txt
macrokeyd-0.1.11.dist-info/RECORD
