Metadata-Version: 2.4
Name: macrokeyd
Version: 0.1.11
Summary: Macro daemon for dedicated keyboards
Author-email: Nhomar Hernandez <nhomar@gmail.com>
Requires-Python: >=3.7
License-File: LICENCE
Requires-Dist: evdev==1.6.1
Requires-Dist: pyudev
Requires-Dist: pyautogui
Requires-Dist: pystray
Requires-Dist: Pillow
Requires-Dist: dbus-python
Requires-Dist: dbus-next
Dynamic: license-file
